valdac/__init__.py
valdac/mixin.py
valdac-0.1.0.dist-info/LICENSE
valdac-0.1.0.dist-info/METADATA
valdac-0.1.0.dist-info/WHEEL
valdac-0.1.0.dist-info/RECORD
